<?xml-stylesheet type='text/xsl' href='prgs.xsl'?><Objects>
  <Charset>UTF-8</Charset>
  <Path>file:///C:/Program Files (x86)/GeneXus/GeneXus18/</Path>
  <Object>
    <ObjCls>0</ObjCls>
    <ObjName>Trn_Resident</ObjName>
    <ObjDesc>Trn_Resident</ObjDesc>
    <ObjLink>trn_resident.aspx</ObjLink>
  </Object>
  <Object>
    <ObjCls>0</ObjCls>
    <ObjName>Trn_NetworkIndividual</ObjName>
    <ObjDesc>Trn_Network Individual</ObjDesc>
    <ObjLink>trn_networkindividual.aspx</ObjLink>
  </Object>
  <Object>
    <ObjCls>0</ObjCls>
    <ObjName>Trn_NetworkCompany</ObjName>
    <ObjDesc>Trn_Network Company</ObjDesc>
    <ObjLink>trn_networkcompany.aspx</ObjLink>
  </Object>
  <Object>
    <ObjCls>0</ObjCls>
    <ObjName>Trn_ResidentType</ObjName>
    <ObjDesc>Trn_Resident Type</ObjDesc>
    <ObjLink>trn_residenttype.aspx</ObjLink>
  </Object>
  <Object>
    <ObjCls>0</ObjCls>
    <ObjName>Trn_MedicalIndication</ObjName>
    <ObjDesc>Trn_Medical Indication</ObjDesc>
    <ObjLink>trn_medicalindication.aspx</ObjLink>
  </Object>
  <Object>
    <ObjCls>0</ObjCls>
    <ObjName>WWPBaseObjects.WWP_UserExtended</ObjName>
    <ObjDesc>WWPBaseObjects.Extended User from GAMUser</ObjDesc>
    <ObjLink>wwpbaseobjects.wwp_userextended.aspx</ObjLink>
  </Object>
  <Object>
    <ObjCls>0</ObjCls>
    <ObjName>WWPBaseObjects.WWP_Entity</ObjName>
    <ObjDesc>WWPBaseObjects.WWP_Entity</ObjDesc>
    <ObjLink>wwpbaseobjects.wwp_entity.aspx</ObjLink>
  </Object>
  <Object>
    <ObjCls>0</ObjCls>
    <ObjName>WWPBaseObjects.Subscriptions.WWP_Subscription</ObjName>
    <ObjDesc>WWPBaseObjects.Subscriptions.WWP_Subscription</ObjDesc>
    <ObjLink>wwpbaseobjects.subscriptions.wwp_subscription.aspx</ObjLink>
  </Object>
  <Object>
    <ObjCls>0</ObjCls>
    <ObjName>WWPBaseObjects.SMS.WWP_SMS</ObjName>
    <ObjDesc>WWPBaseObjects.SMS.WWP_SMS</ObjDesc>
    <ObjLink>wwpbaseobjects.sms.wwp_sms.aspx</ObjLink>
  </Object>
  <Object>
    <ObjCls>0</ObjCls>
    <ObjName>WWPBaseObjects.Notifications.Web.WWP_WebNotification</ObjName>
    <ObjDesc>WWPBaseObjects.Notifications.Web.WWP_Web Notification</ObjDesc>
    <ObjLink>wwpbaseobjects.notifications.web.wwp_webnotification.aspx</ObjLink>
  </Object>
  <Object>
    <ObjCls>0</ObjCls>
    <ObjName>WWPBaseObjects.Notifications.Web.WWP_WebClient</ObjName>
    <ObjDesc>WWPBaseObjects.Notifications.Web.WWP_Web Client</ObjDesc>
    <ObjLink>wwpbaseobjects.notifications.web.wwp_webclient.aspx</ObjLink>
  </Object>
  <Object>
    <ObjCls>0</ObjCls>
    <ObjName>WWPBaseObjects.Notifications.Common.WWP_NotificationDefinition</ObjName>
    <ObjDesc>WWPBaseObjects.Notifications.Common.Notification Definition</ObjDesc>
    <ObjLink>wwpbaseobjects.notifications.common.wwp_notificationdefinition.aspx</ObjLink>
  </Object>
  <Object>
    <ObjCls>0</ObjCls>
    <ObjName>WWPBaseObjects.Notifications.Common.WWP_Notification</ObjName>
    <ObjDesc>WWPBaseObjects.Notifications.Common.Notification</ObjDesc>
    <ObjLink>wwpbaseobjects.notifications.common.wwp_notification.aspx</ObjLink>
  </Object>
  <Object>
    <ObjCls>0</ObjCls>
    <ObjName>WWPBaseObjects.Mail.WWP_MailTemplate</ObjName>
    <ObjDesc>WWPBaseObjects.Mail.Mail Template</ObjDesc>
    <ObjLink>wwpbaseobjects.mail.wwp_mailtemplate.aspx</ObjLink>
  </Object>
  <Object>
    <ObjCls>0</ObjCls>
    <ObjName>WWPBaseObjects.Mail.WWP_Mail</ObjName>
    <ObjDesc>WWPBaseObjects.Mail.Mail</ObjDesc>
    <ObjLink>wwpbaseobjects.mail.wwp_mail.aspx</ObjLink>
  </Object>
  <Object>
    <ObjCls>0</ObjCls>
    <ObjName>WWPBaseObjects.Discussions.WWP_DiscussionMessage</ObjName>
    <ObjDesc>WWPBaseObjects.Discussions.Discussion Message</ObjDesc>
    <ObjLink>wwpbaseobjects.discussions.wwp_discussionmessage.aspx</ObjLink>
  </Object>
  <Object>
    <ObjCls>0</ObjCls>
    <ObjName>WWPBaseObjects.Discussions.WWP_DiscussionMessageMention</ObjName>
    <ObjDesc>WWPBaseObjects.Discussions.Discussion Message Mention</ObjDesc>
    <ObjLink>wwpbaseobjects.discussions.wwp_discussionmessagemention.aspx</ObjLink>
  </Object>
  <Object>
    <ObjCls>0</ObjCls>
    <ObjName>WWPBaseObjects.UserCustomizations</ObjName>
    <ObjDesc>WWPBaseObjects.User Custom</ObjDesc>
    <ObjLink>wwpbaseobjects.usercustomizations.aspx</ObjLink>
  </Object>
  <Object>
    <ObjCls>0</ObjCls>
    <ObjName>Trn_AgendaCalendar</ObjName>
    <ObjDesc>Trn_Agenda Calendar</ObjDesc>
    <ObjLink>trn_agendacalendar.aspx</ObjLink>
  </Object>
  <Object>
    <ObjCls>0</ObjCls>
    <ObjName>Trn_Row</ObjName>
    <ObjDesc>Trn_Row</ObjDesc>
    <ObjLink>trn_row.aspx</ObjLink>
  </Object>
  <Object>
    <ObjCls>0</ObjCls>
    <ObjName>Trn_Col</ObjName>
    <ObjDesc>Trn_Col</ObjDesc>
    <ObjLink>trn_col.aspx</ObjLink>
  </Object>
  <Object>
    <ObjCls>13</ObjCls>
    <ObjName>GAMExampleLogin</ObjName>
    <ObjDesc>Login</ObjDesc>
    <ObjLink>gamexamplelogin.aspx</ObjLink>
  </Object>
  <Object>
    <ObjCls>13</ObjCls>
    <ObjName>GAMNotAuthorized</ObjName>
    <ObjDesc>Not Authorized</ObjDesc>
    <ObjLink>gamnotauthorized.aspx</ObjLink>
  </Object>
  <Object>
    <ObjCls>13</ObjCls>
    <ObjName>GAMHome</ObjName>
    <ObjDesc>Home</ObjDesc>
    <ObjLink>gamhome.aspx</ObjLink>
  </Object>
  <Object>
    <ObjCls>13</ObjCls>
    <ObjName>GAMRegisterUser</ObjName>
    <ObjDesc>Register user</ObjDesc>
    <ObjLink>gamregisteruser.aspx</ObjLink>
  </Object>
  <Object>
    <ObjCls>13</ObjCls>
    <ObjName>GAMSSOLogin</ObjName>
    <ObjDesc>Single Sign-On</ObjDesc>
    <ObjLink>gamssologin.aspx</ObjLink>
  </Object>
  <Object>
    <ObjCls>13</ObjCls>
    <ObjName>Home</ObjName>
    <ObjDesc>Home</ObjDesc>
    <ObjLink>home.aspx</ObjLink>
  </Object>
  <Object>
    <ObjCls>13</ObjCls>
    <ObjName>WorkWithPlus.WWP_ParameterWW</ObjName>
    <ObjDesc>WorkWithPlus.Parameter</ObjDesc>
    <ObjLink>workwithplus.wwp_parameterww.aspx</ObjLink>
  </Object>
  <Object>
    <ObjCls>13</ObjCls>
    <ObjName>WWPBaseObjects.Subscriptions.WWP_SubscriptionsSettings</ObjName>
    <ObjDesc>WWPBaseObjects.Subscriptions.Manage my Subscriptions</ObjDesc>
    <ObjLink>wwpbaseobjects.subscriptions.wwp_subscriptionssettings.aspx</ObjLink>
  </Object>
  <Object>
    <ObjCls>13</ObjCls>
    <ObjName>WWPBaseObjects.Notifications.Common.WWP_VisualizeAllNotifications</ObjName>
    <ObjDesc>WWPBaseObjects.Notifications.Common.Visualize all notifications</ObjDesc>
    <ObjLink>wwpbaseobjects.notifications.common.wwp_visualizeallnotifications.aspx</ObjLink>
  </Object>
  <Object>
    <ObjCls>13</ObjCls>
    <ObjName>WP_NotAuthorized</ObjName>
    <ObjDesc>Not Authorized</ObjDesc>
    <ObjLink>wp_notauthorized.aspx</ObjLink>
  </Object>
  <Object>
    <ObjCls>13</ObjCls>
    <ObjName>Trn_ManagerWW</ObjName>
    <ObjDesc> Managers</ObjDesc>
    <ObjLink>trn_managerww.aspx</ObjLink>
  </Object>
  <Object>
    <ObjCls>13</ObjCls>
    <ObjName>Trn_ThemeWW</ObjName>
    <ObjDesc> Trn_Theme</ObjDesc>
    <ObjLink>trn_themeww.aspx</ObjLink>
  </Object>
  <Object>
    <ObjCls>13</ObjCls>
    <ObjName>Trn_MediaWW</ObjName>
    <ObjDesc> Trn_Media</ObjDesc>
    <ObjLink>trn_mediaww.aspx</ObjLink>
  </Object>
  <Object>
    <ObjCls>13</ObjCls>
    <ObjName>Trn_OrganisationWW</ObjName>
    <ObjDesc> Organisations</ObjDesc>
    <ObjLink>trn_organisationww.aspx</ObjLink>
  </Object>
  <Object>
    <ObjCls>13</ObjCls>
    <ObjName>Trn_OrganisationTypeWW</ObjName>
    <ObjDesc> Trn_Organisation Type</ObjDesc>
    <ObjLink>trn_organisationtypeww.aspx</ObjLink>
  </Object>
  <Object>
    <ObjCls>13</ObjCls>
    <ObjName>Trn_OrganisationSettingWW</ObjName>
    <ObjDesc> Trn_Organisation Setting</ObjDesc>
    <ObjLink>trn_organisationsettingww.aspx</ObjLink>
  </Object>
  <Object>
    <ObjCls>13</ObjCls>
    <ObjName>WP_ApplicationDesign</ObjName>
    <ObjDesc>WP_Application Design</ObjDesc>
    <ObjLink>wp_applicationdesign.aspx</ObjLink>
  </Object>
  <Object>
    <ObjCls>13</ObjCls>
    <ObjName>Trn_TileWW</ObjName>
    <ObjDesc> Tile</ObjDesc>
    <ObjLink>trn_tileww.aspx</ObjLink>
  </Object>
  <Object>
    <ObjCls>13</ObjCls>
    <ObjName>Trn_TemplateWW</ObjName>
    <ObjDesc> Template</ObjDesc>
    <ObjLink>trn_templateww.aspx</ObjLink>
  </Object>
  <Object>
    <ObjCls>13</ObjCls>
    <ObjName>Trn_LocationWW</ObjName>
    <ObjDesc>Location</ObjDesc>
    <ObjLink>trn_locationww.aspx</ObjLink>
  </Object>
  <Object>
    <ObjCls>13</ObjCls>
    <ObjName>Trn_SupplierGenWW</ObjName>
    <ObjDesc> General Suppliers</ObjDesc>
    <ObjLink>trn_suppliergenww.aspx</ObjLink>
  </Object>
  <Object>
    <ObjCls>13</ObjCls>
    <ObjName>Trn_SupplierAgbWW</ObjName>
    <ObjDesc>Agb Suppliers</ObjDesc>
    <ObjLink>trn_supplieragbww.aspx</ObjLink>
  </Object>
  <Object>
    <ObjCls>13</ObjCls>
    <ObjName>Trn_ReceptionistWW</ObjName>
    <ObjDesc> Receptionist</ObjDesc>
    <ObjLink>trn_receptionistww.aspx</ObjLink>
  </Object>
  <Object>
    <ObjCls>13</ObjCls>
    <ObjName>Trn_SupplierAgbTypeWW</ObjName>
    <ObjDesc>Agb Supplier Types</ObjDesc>
    <ObjLink>trn_supplieragbtypeww.aspx</ObjLink>
  </Object>
  <Object>
    <ObjCls>13</ObjCls>
    <ObjName>Trn_SupplierGenTypeWW</ObjName>
    <ObjDesc>General Supplier Types</ObjDesc>
    <ObjLink>trn_suppliergentypeww.aspx</ObjLink>
  </Object>
  <Object>
    <ObjCls>13</ObjCls>
    <ObjName>Trn_ProductServiceWW</ObjName>
    <ObjDesc> Product/Service</ObjDesc>
    <ObjLink>trn_productserviceww.aspx</ObjLink>
  </Object>
  <Object>
    <ObjCls>13</ObjCls>
    <ObjName>Trn_PageWW</ObjName>
    <ObjDesc> Trn_Page</ObjDesc>
    <ObjLink>trn_pageww.aspx</ObjLink>
  </Object>
  <Object>
    <ObjCls>1</ObjCls>
    <ObjName>WWPBaseObjects.WWP_DownloadReport</ObjName>
    <ObjDesc>WWPBaseObjects.Download Report</ObjDesc>
    <ObjLink>wwpbaseobjects.wwp_downloadreport.aspx</ObjLink>
  </Object>
</Objects>