{

"GxObject":{"ObjectType":"BusinessComponent","Name":"WWPBaseObjects.Notifications.Web.WWP_WebClient","idConnectivitySupport":"idInherit","Structure":{"Levels":[{"Name":"Wwp_webclient","ParentLevel":"","LevelName":"WWPBaseObjects.Notifications.Web.WWP_WebClient","Description":"WWP_Web Client","Attributes":[{"Name":"WWPWebClientId","Caption":"","default":"","IsKey":"true","ReadOnly":"false","AttributeType":"char","Description":"","Length":"100","Decimals":"0","Signed":"false","AllowDBNulls":"false","InternalName":"WWPWebClientId","DescriptionAtt":"true","InputPicture":"","Type":"xs:string"},{"Name":"WWPWebClientBrowserId","Caption":"","default":"0","IsKey":"false","ReadOnly":"false","AttributeType":"int","Description":"","Length":"4","Decimals":"0","Signed":"false","AllowDBNulls":"false","Domain":"GeneXusSecurityCommon\\GAMBrowser","InternalName":"WWPWebClientBrowserId","InputPicture":"ZZZ9","Type":"xs:int"},{"Name":"WWPWebClientBrowserVersion","Caption":"","default":"","IsKey":"false","ReadOnly":"false","AttributeType":"vchar","Description":"","Length":"2097152","Decimals":"0","Signed":"false","AllowDBNulls":"false","InternalName":"WWPWebClientBrowserVersion","InputPicture":"","Type":"xs:string"},{"Name":"WWPWebClientFirstRegistered","Caption":"","default":"","IsKey":"false","ReadOnly":"false","AttributeType":"dtime","Description":"","Length":"10","Decimals":"12","Signed":"false","AllowDBNulls":"false","Domain":"WWPBaseObjects\\WWP_DateTimeMillis","InternalName":"WWPWebClientFirstRegistered","InputPicture":"99/99/9999 99:99:99.999","Type":"xs:string"},{"Name":"WWPWebClientLastRegistered","Caption":"","default":"","IsKey":"false","ReadOnly":"false","AttributeType":"dtime","Description":"","Length":"10","Decimals":"12","Signed":"false","AllowDBNulls":"false","Domain":"WWPBaseObjects\\WWP_DateTimeMillis","InternalName":"WWPWebClientLastRegistered","InputPicture":"99/99/9999 99:99:99.999","Type":"xs:string"},{"Name":"WWPUserExtendedId","Caption":"","default":"","IsKey":"false","ReadOnly":"false","AttributeType":"char","Description":"","Length":"40","Decimals":"0","Signed":"false","AllowDBNulls":"true","Domain":"WWPBaseObjects\\WWP_GAMGUID","InternalName":"WWPUserExtendedId","InputPicture":"","Type":"xs:string"}]}]},"Relations":{"ManyToOne":{"references":[{"Name":"Wwpbaseobjects\\WWP_UserExtendedWWPUserExtendedId","BusinessComponent":"Wwpbaseobjects\\WWP_UserExtended","LevelName":"WWPBaseObjects.Notifications.Web.WWP_WebClient","Description":"Extended User from GAMUser","ForeignKey":{"KeyAttributes":[{"Name":"WWPUserExtendedId","Type":"char"}]},"InferredAttributes":{"Attributes":[]}}]}}}
}
